priority_config/PriorityConfig.py
priority_config/__init__.py
priority_config-0.1.1.dist-info/licenses/LICENSE
priority_config-0.1.1.dist-info/METADATA
priority_config-0.1.1.dist-info/WHEEL
priority_config-0.1.1.dist-info/top_level.txt
priority_config-0.1.1.dist-info/RECORD
