Metadata-Version: 2.4
Name: priority-config
Version: 0.1.1
Summary: Universal config resolver with precedence: direct → config → env → default
Author-email: Yusuke Watanabe <Yusuke.Watanabe@scitex.ai>
Maintainer-email: Yusuke Watanabe <Yusuke.Watanabe@scitex.ai>
License-Expression: MIT
Project-URL: Homepage, https://github.com/ywatanabe1989/priority-config
Project-URL: Repository, https://github.com/ywatanabe1989/priority-config
Project-URL: Documentation, https://github.com/ywatanabe1989/priority-config
Keywords: configuration,config,environment,precedence,settings
Classifier: Development Status :: 4 - Beta
Classifier: Intended Audience :: Developers
Classifier: Operating System :: OS Independent
Classifier: Programming Language :: Python :: 3
Classifier: Programming Language :: Python :: 3.8
Classifier: Programming Language :: Python :: 3.9
Classifier: Programming Language :: Python :: 3.10
Classifier: Programming Language :: Python :: 3.11
Classifier: Programming Language :: Python :: 3.12
Classifier: Topic :: Software Development :: Libraries :: Python Modules
Classifier: Topic :: System :: Systems Administration
Requires-Python: >=3.8
License-File: LICENSE
Provides-Extra: dev
Requires-Dist: pytest>=7.0.0; extra == "dev"
Requires-Dist: pytest-cov>=4.0.0; extra == "dev"
Requires-Dist: ruff>=0.1.0; extra == "dev"
Requires-Dist: mypy>=1.0.0; extra == "dev"
Requires-Dist: build>=0.10.0; extra == "dev"
Requires-Dist: twine>=4.0.0; extra == "dev"
Dynamic: license-file
